taxpasta/__init__.py
taxpasta/__main__.py
taxpasta/_version.py
taxpasta/py.typed
taxpasta/application/__init__.py
taxpasta/application/add_tax_info_command.py
taxpasta/application/consensus_application.py
taxpasta/application/sample_handling_application.py
taxpasta/application/error/__init__.py
taxpasta/application/error/standardisation_error.py
taxpasta/application/error/taxpasta_error.py
taxpasta/application/service/__init__.py
taxpasta/application/service/_types.py
taxpasta/application/service/profile_reader.py
taxpasta/application/service/profile_standardisation_service.py
taxpasta/application/service/standard_profile_writer.py
taxpasta/application/service/table_reader.py
taxpasta/application/service/tidy_observation_table_writer.py
taxpasta/application/service/wide_observation_table_writer.py
taxpasta/domain/__init__.py
taxpasta/domain/model/__init__.py
taxpasta/domain/model/sample.py
taxpasta/domain/model/standard_profile.py
taxpasta/domain/model/tidy_observation_table.py
taxpasta/domain/model/wide_observation_table.py
taxpasta/domain/service/__init__.py
taxpasta/domain/service/consensus_builder.py
taxpasta/domain/service/sample_merging_service.py
taxpasta/domain/service/taxonomy_service.py
taxpasta/infrastructure/__init__.py
taxpasta/infrastructure/application/__init__.py
taxpasta/infrastructure/application/_dependency_check_mixin.py
taxpasta/infrastructure/application/application_service_registry.py
taxpasta/infrastructure/application/sample_sheet.py
taxpasta/infrastructure/application/standard_profile_file_format.py
taxpasta/infrastructure/application/supported_profiler.py
taxpasta/infrastructure/application/table_reader_file_format.py
taxpasta/infrastructure/application/tidy_observation_table_file_format.py
taxpasta/infrastructure/application/wide_observation_table_file_format.py
taxpasta/infrastructure/application/bracken/__init__.py
taxpasta/infrastructure/application/bracken/bracken_profile.py
taxpasta-0.7.0.dist-info/METADATA
taxpasta-0.7.0.dist-info/WHEEL
taxpasta-0.7.0.dist-info/entry_points.txt
taxpasta-0.7.0.dist-info/licenses/LICENSE
taxpasta-0.7.0.dist-info/RECORD
