Metadata-Version: 2.3
Name: taxpasta
Version: 0.7.0
Summary: TAXonomic Profile Aggregation and STAndardisation
Project-URL: Homepage, https://github.com/taxprofiler/taxpasta
Project-URL: Documentation, https://taxpasta.readthedocs.io
Project-URL: Source Code, https://github.com/taxprofiler/taxpasta
Project-URL: Bug Tracker, https://github.com/taxprofiler/taxpasta/issues
Project-URL: Download, https://pypi.org/project/taxpasta/#files
Author-email: "Moritz E. Beber" <moritz.beber@posteo.de>, Maxime Borry <maxime_borry@eva.mpg.de>, "James A. Fellows Yates" <jfy133@gmail.com>, Sofia Stamouli <sofia.stamouli@scilifelab.se>
License-Expression: Apache-2.0
License-File: LICENSE
Keywords: bioinformatics,classification,merging,metagenomic profile,metagenomics,profiling,standardisation,taxonomic profile,taxonomy
Classifier: Development Status :: 4 - Beta
Classifier: Intended Audience :: Science/Research
Classifier: License :: OSI Approved :: Apache Software License
Classifier: Natural Language :: English
Classifier: Operating System :: OS Independent
Classifier: Programming Language :: Python :: 3 :: Only
Classifier: Programming Language :: Python :: 3.8
Classifier: Programming Language :: Python :: 3.9
Classifier: Programming Language :: Python :: 3.10
Classifier: Programming Language :: Python :: 3.11
Classifier: Topic :: Scientific/Engineering :: Bio-Informatics
Requires-Python: >=3.8
Requires-Dist: depinfo~=2.2
Requires-Dist: numpy~=1.20
Requires-Dist: pandas~=1.4
Requires-Dist: pandera~=0.14
Requires-Dist: taxopy~=0.12
Requires-Dist: typer~=0.6
Provides-Extra: all
Requires-Dist: biom-format; extra == 'all'
Requires-Dist: odfpy; extra == 'all'
Requires-Dist: openpyxl; extra == 'all'
Requires-Dist: pyarrow; extra == 'all'
Requires-Dist: rich; extra == 'all'
Provides-Extra: arrow
Requires-Dist: pyarrow; extra == 'arrow'
Provides-Extra: biom
Requires-Dist: biom-format; extra == 'biom'
Provides-Extra: dev
Requires-Dist: bash-kernel; extra == 'dev'
Requires-Dist: jupyter; extra == 'dev'
Requires-Dist: mkdocs-awesome-pages-plugin~=2.8; extra == 'dev'
Requires-Dist: mkdocs-exclude~=1.0; extra == 'dev'
Requires-Dist: mkdocs-material~=9.1; extra == 'dev'
Requires-Dist: mkdocstrings[python]~=0.20; extra == 'dev'
Requires-Dist: pre-commit; extra == 'dev'
Requires-Dist: tabulate~=0.9; extra == 'dev'
Requires-Dist: tox~=4.0; extra == 'dev'
Provides-Extra: ods
Requires-Dist: odfpy; extra == 'ods'
Provides-Extra: parquet
Requires-Dist: pyarrow; extra == 'parquet'
Provides-Extra: rich
Requires-Dist: rich; extra == 'rich'
Provides-Extra: xlsx
Requires-Dist: openpyxl; extra == 'xlsx'
